hp_procurvearuba/__init__.py
hp_procurvearuba/procurvearuba.py
hp_procurvearuba-2.0.0.dist-info/LICENSE
hp_procurvearuba-2.0.0.dist-info/METADATA
hp_procurvearuba-2.0.0.dist-info/WHEEL
hp_procurvearuba-2.0.0.dist-info/top_level.txt
hp_procurvearuba-2.0.0.dist-info/RECORD
