Metadata-Version: 2.1
Name: hp-procurvearuba
Version: 2.0.0
Summary: Provides a class with custom functions for easy management of hp procurve and aruba switches
Home-page: https://github.com/adraf82/hp_procurvearuba
Author: Adeel Rauf
Author-email: adraf2000@gmail.com
Classifier: License :: OSI Approved :: MIT License
Classifier: Programming Language :: Python :: 3.8
Classifier: Programming Language :: Python :: 3.9
Requires-Python: >=3.6
License-File: LICENSE
Requires-Dist: appdirs (==1.4.4)
Requires-Dist: attrs (==20.3.0)
Requires-Dist: bcrypt (==3.2.0)
Requires-Dist: black (==21.10b0)
Requires-Dist: bleach (==5.0.0)
Requires-Dist: build (==0.7.0)
Requires-Dist: certifi (==2021.10.8)
Requires-Dist: cffi (==1.14.4)
Requires-Dist: charset-normalizer (==2.0.12)
Requires-Dist: click (==7.1.2)
Requires-Dist: commonmark (==0.9.1)
Requires-Dist: cryptography (==3.3.1)
Requires-Dist: docutils (==0.18.1)
Requires-Dist: forwardable (==0.4.1)
Requires-Dist: future (==0.18.2)
Requires-Dist: idna (==3.3)
Requires-Dist: importlib-metadata (==3.6.0)
Requires-Dist: importlib-resources (==3.3.0)
Requires-Dist: iniconfig (==1.1.1)
Requires-Dist: jeepney (==0.8.0)
Requires-Dist: keyring (==23.5.0)
Requires-Dist: mccabe (==0.6.1)
Requires-Dist: mock (==4.0.3)
Requires-Dist: mypy-extensions (==0.4.3)
Requires-Dist: netmiko (==4.1.2)
Requires-Dist: ntc-templates (==3.0.0)
Requires-Dist: packaging (==20.8)
Requires-Dist: paramiko (==2.7.2)
Requires-Dist: pathspec (==0.9.0)
Requires-Dist: pep517 (==0.12.0)
Requires-Dist: pkginfo (==1.8.2)
Requires-Dist: pluggy (==0.13.1)
Requires-Dist: py (==1.10.0)
Requires-Dist: pycodestyle (==2.6.0)
Requires-Dist: pycparser (==2.20)
Requires-Dist: pydocstyle (==6.1.1)
Requires-Dist: pyflakes (==2.3.1)
Requires-Dist: Pygments (==2.12.0)
Requires-Dist: pylama (==7.7.1)
Requires-Dist: PyNaCl (==1.4.0)
Requires-Dist: pyparsing (==2.4.7)
Requires-Dist: pyserial (==3.5)
Requires-Dist: pytest (==6.2.0)
Requires-Dist: pytest-mock (==3.5.1)
Requires-Dist: PyYAML (==5.3.1)
Requires-Dist: readme-renderer (==35.0)
Requires-Dist: regex (==2020.11.13)
Requires-Dist: requests (==2.27.1)
Requires-Dist: requests-toolbelt (==0.9.1)
Requires-Dist: rfc3986 (==2.0.0)
Requires-Dist: rich (==12.4.1)
Requires-Dist: scp (==0.13.3)
Requires-Dist: SecretStorage (==3.3.2)
Requires-Dist: six (==1.15.0)
Requires-Dist: snowballstemmer (==2.1.0)
Requires-Dist: tenacity (==6.2.0)
Requires-Dist: textfsm (==1.1.2)
Requires-Dist: toml (==0.10.2)
Requires-Dist: tomli (==1.2.3)
Requires-Dist: twine (==4.0.0)
Requires-Dist: typed-ast (==1.4.2)
Requires-Dist: typing-extensions (==4.0.0)
Requires-Dist: urllib3 (==1.26.9)
Requires-Dist: webencodings (==0.5.1)
Requires-Dist: zipp (==3.4.0)
